tfq_finance/__init__.py
tfq_finance/execution/__init__.py
tfq_finance/execution/algo_trading.py
tfq_finance/execution/dark_pool_liquidity.py
tfq_finance/execution/execution_performance.py
tfq_finance/execution/high_frequency_trading.py
tfq_finance/execution/latency_arbitrage.py
tfq_finance/execution/market_impact_models.py
tfq_finance/execution/market_making.py
tfq_finance/execution/news_based_trading.py
tfq_finance/execution/optimal_execution.py
tfq_finance/execution/order_placement.py
tfq_finance/execution/pairs_trading.py
tfq_finance/execution/quantitative_momentum.py
tfq_finance/execution/risk_adjusted_execution.py
tfq_finance/execution/sentiment_based_trading.py
tfq_finance/execution/smart_order_routing.py
tfq_finance/execution/statistical_arbitrage.py
tfq_finance/execution/transaction_cost_analysis.py
tfq_finance/execution/volatility_arbitrage.py
tfq_finance/ml/__init__.py
tfq_finance/ml/adversarial_training.py
tfq_finance/ml/anomaly_detection.py
tfq_finance/ml/clustering.py
tfq_finance/ml/data_preparation.py
tfq_finance/ml/explainable_ai.py
tfq_finance/ml/feature_selection.py
tfq_finance/ml/federated_learning.py
tfq_finance/ml/hyperparameter_optimization.py
tfq_finance/ml/meta_learning.py
tfq_finance/ml/model_evaluation.py
tfq_finance/ml/model_interpretability.py
tfq_finance/ml/model_training.py
tfq_finance/ml/quantum_autoencoders.py
tfq_finance/ml/quantum_bayesian_networks.py
tfq_finance/ml/quantum_classification.py
tfq_finance/ml/quantum_generative_advesarial_networks.py
tfq_finance/ml/quantum_neural_networks.py
tfq_finance/ml/quantum_regression.py
tfq_finance/ml/reinforcement_learning.py
tfq_finance/ml/sentiment_analysis.py
tfq_finance/ml/synthetic_data_generation.py
tfq_finance/ml/time_series_forecasting.py
tfq_finance/optimization/__init__.py
tfq_finance/optimization/alpha_generation.py
tfq_finance/optimization/asset_allocation.py
tfq_finance/optimization/factor_investing.py
tfq_finance/optimization/factor_model_optimization.py
tfq_finance-1.0.3.dist-info/LICENSE
tfq_finance-1.0.3.dist-info/METADATA
tfq_finance-1.0.3.dist-info/WHEEL
tfq_finance-1.0.3.dist-info/top_level.txt
tfq_finance-1.0.3.dist-info/RECORD
