Metadata-Version: 2.1
Name: tfq-finance
Version: 1.0.3
Summary: A quantum machine learning library for quantitative finance built on top of TensorFlow Quantum
Home-page: https://github.com/jialuechen/tfq-finance
Author: jialuechen
Author-email: jialuechen@outlook.com
Classifier: Programming Language :: Python :: 3.7
Classifier: License :: OSI Approved :: Apache Software License
Classifier: Operating System :: OS Independent
Requires-Python: >=3.7
License-File: LICENSE
Requires-Dist: tensorflow (==2.11.0)
Requires-Dist: tensorflow-quantum
Requires-Dist: cirq
Requires-Dist: numpy
Requires-Dist: sympy
Requires-Dist: scipy
Requires-Dist: pandas
Requires-Dist: matplotlib
Requires-Dist: scikit-learn
